murd/__init__.py
murd/murd.py
murd-0.0.5.8.dist-info/LICENSE
murd-0.0.5.8.dist-info/METADATA
murd-0.0.5.8.dist-info/WHEEL
murd-0.0.5.8.dist-info/top_level.txt
murd-0.0.5.8.dist-info/RECORD
