Metadata-Version: 2.1
Name: murd
Version: 0.0.5.8
Summary: Matrix: update, read, delete. A data store with a sorted, key:value store model
Home-page: https://gitlab.com/musingsole/murd
Author: musingsole
Author-email: musingsole@gmail.com
License: UNKNOWN
Platform: UNKNOWN
Classifier: Programming Language :: Python :: 3
Classifier: License :: OSI Approved :: MIT License
Classifier: Operating System :: OS Independent
License-File: LICENSE
